CHANGELOG.md
MANIFEST.in
README.md
setup.py
mimus/__init__.py
mimus/config.py
mimus/handler.py
mimus/service.py
mimus.egg-info/PKG-INFO
mimus.egg-info/SOURCES.txt
mimus.egg-info/dependency_links.txt
mimus.egg-info/top_level.txt
mimus/config/__init__.py
mimus/config/parser.py
tests/__init__.py
tests/test_helloworld.py