Metadata-Version: 2.1
Name: mimus
Version: 0.0.0
Summary: create mock service with ease
Home-page: https://github.com/IanChen83/mimus
Author: Ian Chen
Author-email: ianchen83.tw@gmail.com
License: License :: OSI Approved :: MIT License
Platform: UNKNOWN
Classifier: Development Status :: 1 - Planning
Classifier: Intended Audience :: Developers
Classifier: Topic :: Internet :: WWW/HTTP :: HTTP Servers
Classifier: Topic :: Software Development :: Testing :: Mocking
Classifier: Programming Language :: Python :: 3.5
Classifier: Programming Language :: Python :: 3.6
Classifier: Programming Language :: Python :: 3.7
